{
  "sack": "мешок",
  "sacred": "священный",
  "sacrifice": "жертва",
  "saddle": "седло",
  "safe": "надёжный, защищённый",
  "sail": "парус, плыть (о судне)",
  "saint": "святой",
  "salary": "зарплата",
  "sale": "продажа, сбыт",
  "salesperson": "продавец (в магазине)",
  "salient": "выступающий, заметный",
  "saliva": "слюна",
  "salmon": "лосось",
  "salt": "соль",
  "salvage": "спасти, уберечь от потери",
  "salvation": "спасение",
  "sample": "образец, часть",
  "sanctuary": "убежище или заповедник",
  "sand": "песок",
  "sane": "здравый, вменяемый",
  "satellite": "спутник",
  "satisfy": "удовлетворять",
  "saturated": "насыщенный",
  "saucepan": "кастрюля или сковорода",
  "saucer": "блюдце",
  "sausage": "колбаса",
  "savage": "дикарь, дикий (в т. ч. перен.)",
  "save up": "накопить",
  "savings": "сбережения",
  "savior": "спаситель",
  "savor": "вкус, смаковать",
  "scaffold": "помост",
  "scale": ["чешуя, шелуха", "взбираться", "масштаб, шкала"],
  "scales": "весы",
  "scant": "скудный",
  "scar": "шрам",
  "scarce": "редкий, скудный",
  "scare": "пугать",
  "scarf": "шарф",
  "scarlet": "алый",
  "scatter": "разбрасывать, рассеивать",
  "scent": "нюх или аромат",
  "schedule": "график, расписание",
  "scheme": "схема",
  "scholar": "учёный",
  "scholarship (money)": "стипендия",
  "science": "наука",
  "scissors": "ножницы",
  "scold": "ругать",
  "scoop": " совок, ковш, черпать",
  "scope": "пределы, район",
  "score": "счёт, очко, балл",
  "scorn": "презирать, презрение",
  "scour": "обыскать, прочесать",
  "scout": "разведчик",
  "scowl": "насупиться, рассердиться",
  "scramble": ["драка, схватка", "карабкаться, продираться"],
  "scrambled eggs": "яичница",
  "scrap": "обломок, обрывок",
  "scrape": "скрести",
  "scrape through": "с трудом пройти",
  "scrape together": "наскрести (денег)",
  "scratch": "царапать, царапина",
  "scream": "кричать, крик, вопль ",
  "screech": "визг, скрип, хрип и т. д.",
  "screenplay": "сценарий",
  "screw": ["винт, ввинчивать", "к чёрту"],
  "screw up": "завалить, просрать",
  "scribble": "криво написать, нацарапать",
  "scrub": "чистить, драить",
  "scrutiny": "внимательный осмотр, изучение",
  "scurry": "бежать, сновать, суетиться",
  "seal": ["печать, запечатывать", "тюлень"],
  "seam": "шов",
  "search": "поиски, искать",
  "seasoning": "приправа",
  "seat": "место, сиденье",
  "secular": "светский",
  "secure": "безопасный, надёжный",
  "sediment": "осадок",
  "seduce": "соблазнять",
  "see off": "провожать (в путь)",
  "see through": "довести до конца",
  "see to": "заняться, позаботиться",
  "seed": "семя, сеять",
  "seek (sought, sought)": "искать, стремиться",
  "seem": "казаться",
  "seep": "просачиваться, проникать",
  "segregate": "разделять",
  "seize": "схватить",
  "seldom": "редко",
  "select": "выбирать, отбирать",
  "selfish": "эгоистичный",
  "sell out of": "распродать (весь товар)",
  "send (sent, sent)": "отправить",
  "send out": "рассылать",
  "senior": "старший",
  "sensation": "ощущение",
  "sense": ["чувство, осознание", "смысл, значение"],
  "sensible": "разумный, имеющий смысл",
  "sensitive": "чувствительный",
  "sentence": ["предложение", "приговор"],
  "sentiment": "настроение, чувство",
  "separate": "отдельный, отделять",
  "sequence": "последовательность",
  "serene": "безмятежный, безоблачный",
  "series": "сериал",
  "sermon": "проповедь",
  "serve": ["служить", "сидеть (в тюрьме)", "подавать (блюдо)"],
  "set": "набор, комплект",
  "set (set, set)": "установить, наладить",
  "set about": "приступить, начать",
  "set down": "написать, установить",
  "set out": "разъяснять",
  "set out for": "отправиться",
  "set smb back": ["задержать", "обойтись в (сумму)"],
  "set smb up": "подставить",
  "set smb up with": ["устроить, организовать", "познакомить, свести"],
  "settle": ["уладить", "селиться"],
  "settle for": "согласиться на",
  "settle in": "освоиться",
  "settle on": "определиться с",
  "sever": "разрывать, разъединять",
  "several": "несколько",
  "severe": "серьёзный, суровый, жёсткий",
  "sew": "шить",
  "sewage": "канализация, сточные воды",
  "sex": "пол",
  "shabby": "облезлый, убогий",
  "shack": "лачуга, хибара, будка",
  "shade": ["тень", "оттенок (яркости)"],
  "shadow": "тень",
  "shaft": ["вал, ось, стержень", "шахта (напр. лифта)"],
  "shake (shook, shaken)": ["трясти", "пожать (руки)"],
  "shake off": "отделаться",
  "shake up": "встряхнуть, взбудоражить",
  "shallow": "мелкий",
  "shame": "стыд, позор",
  "shape": "форма, формировать",
  "share": ["делить, доля", "разделять (напр. мнение)"],
  "shareholder": "акционер",
  "shark": "акула",
  "sharp": "острый",
  "shatter": "разрушить, раздробить",
  "shave": "брить",
  "shed": "сарай, ангар и т.п.",
  "shed (shed, shed)": "проливать, терять, сбрасывать",
  "sheep (pl:sheep)": "овца",
  "sheer": ["явный, полный, чистый", "отвесный"],
  "sheet": "лист",
  "shelf (pl: shelves)": "полка, уступ",
  "shell": "скорлупа, раковина, гильза",
  "shelter": "укрытие, убежище",
  "shepherd": "пастух",
  "shield": "щит, прикрывать",
  "shift": ["сменить, сдвинуть", "смена (на работе)"],
  "shimmer": "мерцать, переливаться",
  "shine (shone, shined)": "сиять, блестеть, светить",
  "ship": "доставлять",
  "shirt": "рубашка",
  "shiver": "дрожь, дрожать",
  "shoe": "туфля, ботинок (низкий)",
  "shoot (shot, shot)": ["стрелять", "снимать, фотографировать"],
  "shore": "берег",
  "shortage": "нехватка",
  "shoulder": "плечо",
  "shout": "кричать",
  "shove": "резко толкнуть, пихнуть",
  "shovel": "лопата или совок",
  "show around": "показать места",
  "show off": "показать всем, похвастаться",
  "show up": "прийти, появиться",
  "showcase": "витрина, демонстрировать",
  "shower": "душ",
  "shred": "мелко порубить",
  "shrewd": "проницательный",
  "shriek": "пронзительный крик, вскрикнуть",
  "shrimp": "креветка",
  "shrine": "святыня",
  "shrink (shrank, shrunk)": "сжаться, съёжиться",
  "shroud": "пелена, окутывать",
  "shrub": "куст",
  "shrug": "пожать плечами",
  "shudder": "содрогаться, дрожь",
  "shuffle": "перемешивать, тасовать",
  "shun": "избегать",
  "shut (shut, shut)": "закрыть",
  "shut out": "не впускать",
  "shut up": "заткнуться",
  "shy": "застенчивый",
  "siblings": "братья и сестры",
  "sick": "больной, плохо чувствующий",
  "sideline": "что-то вторичное",
  "sidewalk": "тротуар",
  "sideways": "вбок",
  "siege": "осада",
  "sift": "просеять",
  "sigh": "вздох",
  "sight": ["вид, поле зрения", "достопримечаетльность"],
  "sign": ["знак", "подпись, подписывать"],
  "sign up": "записаться, зарегистрироваться",
  "signature": "подпись",
  "significant": "значительный",
  "signify": "означать",
  "silent": "тихий, молчаливый",
  "silk": "шелк",
  "sill": "подоконник, порог",
  "silly": "глупый",
  "similar": "похожий",
  "simmer": "медленно кипятить",
  "simple": "простой, обычный",
  "simulate": "моделировать, имитировать",
  "simultaneous": "одновременный",
  "sin": "грех, грешить",
  "since": ["поскольку", "с (какого-то времени)"],
  "sincere": "искренний",
  "single": "один, отдельный, единый",
  "singular": "единственный, особый",
  "sinister": "зловещий",
  "sink": "раковина",
  "sink (sank, sunk)": "тонуть, топить",
  "sip": "глоток",
  "sit around": "просто сидеть",
  "sit back": "отсидеться",
  "sit out": "высидеть",
  "site": "местоположение",
  "situate": "располагать",
  "size up": "изучить, оценить",
  "skate": "конёк, кататься на коньках",
  "sketch": "набросок, эскиз",
  "ski": "ездить на лыжах",
  "skid": "заносить, скользить, буксовать",
  "skill": "умение, искусство и т. д.",
  "skillet": "сковорода (глубокая)",
  "skim": "скользить (легко)",
  "skin": "кожа",
  "skinny": "тощий",
  "skip": "прыгать, перепрыгивать",
  "skirt": "юбка",
  "skull": "череп",
  "slab": "плита, блок",
  "slack": "расслабление, поблажка",
  "slam": "хлопать, ударять, захлопывать",
  "slant": "наклон, скос, наклонять",
  "slap": "шлёпать, пощечина",
  "slash": "рубить, хлестать, кромсать",
  "slate": "шифер или сланец",
  "slaughter": "бойня (в т. ч. перен.), забивать",
  "slave": "раб",
  "slay (slew, slain)": "умертвить",
  "sleek": "гладкий, лоснящийся",
  "sleep around": "трахаться, блудить",
  "sleeve": "рукав",
  "slender": "тонкий, стройный, изящный",
  "slice": "ломтик, нарезать",
  "slick": "скользкий",
  "slide (slid, slid)": "скользить",
  "slight": "лёгкий, слабый, незначительный",
  "slim": "стройный",
  "slime": "слизь",
  "slip": "скользнуть",
  "slipper": "тапок",
  "slippery": "скользкий",
  "slit": "щель",
  "slope": "склон, наклон",
  "sloppy": "небрежный, неряшливый",
  "slot": "разъём, паз, гнездо",
  "slow down": "замедлиться",
  "sludge": "осадок, отстой, ил",
  "slum": "трущобы",
  "slump": "спад, сваливаться",
  "slut": "шлюха",
  "sly": "лукавый, коварный",
  "smack": "шлёпнуть, хлопнуть",
  "smart": "умный, хитрый",
  "smash": "громить, разбивать",
  "smear": "мазать",
  "smell": "запах, пахнуть, нюхать",
  "smirk": "ухмылка",
  "smooth": "гладкий",
  "smother": "задушить",
  "smudge": "смазать",
  "smuggle": "провозить тайно",
  "snack": "лёгкая закуска",
  "snag": "коряга или загвоздка",
  "snail": "улитка",
  "snake": "змея",
  "snap": "щёлкать, щелчок",
  "snapshot": "снимок",
  "snarl": "рычать, огрызаться",
  "snatch": "схватить, утащить",
  "sneak": "красться",
  "sneakers": "кеды, кроссовки",
  "sneer": "усмешка, насмехаться",
  "sneeze": "чихать",
  "sniff": "нюхать, сопеть, фы и т. д.",
  "snore": "храп, храпеть",
  "snort": "фыркнуть, хмыкнуть",
  "snowball": "снежок",
  "snug": "уютный, тесный",
  "so far": "до сих пор",
  "soak": "мочить, пропитывать",
  "soap": "мыло",
  "soar": "парить, взмывать (втч. о ценах)",
  "sob": "рыдать, всхлипывать",
  "sober": "трезвый",
  "sober up": "протрезветь",
  "so-called": "так называемый",
  "soccer": "футбол",
  "society": "общество",
  "sock": "носок",
  "socket": "разъем, розетка",
  "soften": "смягчать",
  "software": "программое обеспечение",
  "soil": "почва",
  "solar": "солнечный",
  "sole": ["единственный", "подошва"],
  "solemn": "торжественный, серьёзный",
  "solid": ["сплошной", "твёрдый, крепкий"],
  "solitary": "уединенный",
  "solitude": "одиночество",
  "solution": ["решение, ответ", "раствор"],
  "solve": "решить",
  "someday": "когда-нибудь",
  "somewhat": "слегка",
  "soon": "скоро или рано",
  "soot": "сажа",
  "soothe": "успокаивать",
  "sophisticated": "сложный, изощрённый",
  "sore": "больной, рана",
  "sorrow": "горе, скорбь",
  "sound": "здоровый",
  "sour": "кислый",
  "source": "источник",
  "south": "юг, южный",
  "sovereign": "суверенный",
  "sow (sowed, sown)": "сеять",
  "space": ["пространство", "космос"],
  "spade": "лопата",
  "span": "пролёт, интервал",
  "spare": ["щадить, избавить", "запасной, лишний", "выделить, уделить"],
  "spark": "искра, вспыхивать",
  "sparkle": "сверкать, блистать, искриться",
  "sparse": "редкий, разреженный",
  "spawn": "порождать, порождение и т. д.",
  "speak out": "высказать",
  "speak up": "говорить громче",
  "spear": "копье",
  "special": "особенный, специальный",
  "species": "вид (биол.)",
  "specific": "конкретный",
  "specify": "указать, установить, уточнить",
  "specimen": "образец, экземпляр",
  "speck": "пятнышко, крупинка",
  "spectacle": "зрелище",
  "spectator": "зритель, наблюдатель",
  "speculate": "предполагать, строить догадки",
  "speed up": "ускориться",
  "spell": ["заклинание, чары", "произносить (писать) по буквам"],
  "spell out": "разъяснить",
  "spend (spent, spent)": "тратить, проводить (время)",
  "spice": "пряность, специя",
  "spike": "шип, штырь, острие, клин",
  "spill": "проливать, рассыпать",
  "spin": "крутить",
  "spine": "позвоночник",
  "spirit": "дух",
  "spit (spat, spat)": "плевать",
  "splash": "брызги, всплеск",
  "splendid": "великолепный, блестящий",
  "splinter": "шепка, осколок, заноза",
  "split (split, split)": "расколоться, распасться",
  "split up": "разделиться",
  "spoil": "портить",
  "spokesman": "представитель, прес-секретарь",
  "sponge": "губка",
  "spooky": "жуткий",
  "spot": ["место", "пятно", "заметить, увидеть"],
  "spotlight": "прожектор, центр внимания",
  "spouse": "супруг, супруга",
  "sprawl": "растягиваться, расползаться",
  "spread (spread, spread)": "распространять(ся)",
  "spring (sprang, sprung)": ["прыгать", "источник, проистекать"],
  "sprinkle": "побрызгать, посыпать",
  "sprout": "росток, прорастать",
  "spur": "шпора, побуждать",
  "spy(on)": "шпион, шпионить",
  "squad": "команда, отряд",
  "square": ["квадрат, квадратный", "площадь"],
  "squash": "раздавливать, расплющивать",
  "squat": "приседать, приземистый",
  "squeak": "пищать, скрипеть",
  "squeal": "визг, визжать",
  "squeeze": "сжимать",
  "squid": "кальмар",
  "squint": "щуриться или коситься",
  "squirm": "извиваться, ёрзать",
  "squirrel": "белка",
  "squirt": "тонкая струя",
  "stab": "ударить ножом, зарезать",
  "stable": "устойчивый",
  "stack": "стопка, куча, складывать",
  "staff": "персонал",
  "stage": ["сцена", "стадия, ступень"],
  "stagger": "шататься, колебаться",
  "stain": "пятно, окрашиваться, пачкать",
  "stairs": "ступеньки, лестница",
  "stake": ["стойка, кол, столб", "ставка, делать ставку"],
  "stale": "несвежий",
  "stalk": ["красться, преследовать", "стебель"],
  "stall": ["задержаться, застопориться", "палатка, ларёк"],
  "stamp": "печать, штамп, марка",
  "stance": "поза, положение",
  "stand": "терпеть, выносить",
  "stand against": "противостоять",
  "stand by": "поддерживать, быть наготове",
  "stand for": ["выступать за", "обозначать (в сокращении)"],
  "stand out": "выделяться",
  "standpoint": "точка зрения",
  "staple": "скоба, скрепка",
  "stare": "пялиться, пристальный взгляд",
  "stark": "чёткий, жёсткий, острый (об. перен.)",
  "start up": "основать, установить",
  "startle": "испугать (неожиданностью)",
  "starve": "голодать",
  "stash": "тайник, заначка,  прятать",
  "state": ["государство", "состояние", "заявить, отметить"],
  "stature": "рост",
  "statutory": "установленный законом",
  "stay": ["оставаться", "остановиться пожить"],
  "stay up": "не ложиться",
  "steady": "устойчивый",
  "steal (stole, stolen)": "красть",
  "stealth": "скрытность, хитрость",
  "steam": "пар",
  "steel": "сталь, стальной",
  "steep": "крутой",
  "steer": "управлять, направлять",
  "stellar": "звездный",
  "stem": "стебель",
  "step": "шаг, ступать, ступенька",
  "step down": "уйти в отставку",
  "step in": "вмешаться",
  "stern": "суровый, строгий",
  "stew": "тушить, рагу",
  "stick": "палка, тыкать палкой",
  "stick (stuck, stuck)": "приклеить",
  "stick at": "упорно продолжать",
  "stick out": "торчать, выделяться",
  "stick to": "придерживаться, соблюдать",
  "stick together": "держаться вместе",
  "stiff": "жёсткий, негнущийся",
  "stifle": "удушать",
  "still": "спокойный, неподвижный",
  "sting (stung, stung)": "жалить, жало",
  "stink (stank, stunk)": "вонять",
  "stir": "шевелить(ся), двигать и т.д.",
  "stir up": "вызвать, возбудить",
  "stitch": "стежок, сшить, зашить",
  "stock": ["запас", "акции"],
  "stock up on": "запастись",
  "stocking": "чулок",
  "stomach": "желудок, живот",
  "stomp": "топать",
  "stool": "табурет",
  "stoop": ["крыльцо со ступеньками (амер.)", "наклоняться или сутулиться"],
  "stop over": "заехать, остановиться",
  "store": ["хранить, хранилище", "магазин"],
  "stout": "толстый, плотный, крепкий",
  "stove": "плита",
  "straight": "прямой, прямо",
  "straightforward": "простой, прямой, откровенный",
  "strain": "напрягать, напряжение",
  "strait": "пролив",
  "strand": ["застрять, сесть на мель", "прядь, нить (об. скрученная)"],
  "strangle": "придушить",
  "strap": "ремень",
  "straw": "солома",
  "strawberry": "клубника",
  "stray": "бродить, бродячий",
  "streak": "полоса, след, струя",
  "stream": "поток, ручей",
  "strength": "сила, мощность, прочность",
  "stress": "подчеркнуть, заострить внимание",
  "stretch": "тянуть, вытягивать",
  "strew (strewn, strewn)": "разбрасывать",
  "strict": "строгий, точный",
  "stride (strode, stridden)": "шагать, шаг",
  "strike": "забастовка",
  "strike (struck, struck)": "бить, удар",
  "strike out": "потерпеть неудачу",
  "string": "струна, тетива, бечева",
  "stringent": "строгий",
  "strip": ["полоса, лента", "снимать (обнажать)"],
  "stripe": "полоса",
  "strive (strove, striven)": "стремиться, добиваться",
  "stroke": "гладить",
  "stroll": "прогулка, прогуливаться",
  "struggle": "бороться, борьба",
  "stubborn": "упрямый",
  "stud": "шпилька",
  "stuff": "вещи, всякая фигня",
  "stuffy": "душный",
  "stumble": "спотыкаться, запинаться",
  "stump": "пень",
  "stun": "ошеломить, оглушить",
  "stunt": "трюк, выходка",
  "stupid": "глупый",
  "sturdy": "крепкий",
  "subdue": "подавить, укротить",
  "subject": ["предмет, тема", "подверженный, подвергать"],
  "sublime": "возвышенный, величественный",
  "submerge": "погружаться под воду",
  "submit": "подавать информацию",
  "submit to": "подчиниться",
  "subordinate": "подчиненный, подчинять",
  "subscribe": "подписываться",
  "subsequent": "последующий",
  "subside": "утихать, спадать",
  "subsidiary": "вспомогательный, дополнительный",
  "subsist": "существовать, прокормиться",
  "substance": "вещество, материя",
  "substantial": "существенный, значительный",
  "substantive": "существенный, основной",
  "substitute": "заменять, замена",
  "subtitle": "субтитры или подзаголовок",
  "subtle": "тонкий, неуловимый",
  "subtract": "вычитать",
  "suburb": "пригород",
  "subvert": "подорвать",
  "subway": "метро (амер.)",
  "succeed": "достичь цели",
  "success": "успех",
  "succession": "последовательность, преемственность",
  "successor": "преемник",
  "succumb": "поддаться, не устоять",
  "suck": "сосать",
  "sudden": "внезапный",
  "sue": "предъявить иск",
  "suffer": "страдать",
  "suffice": "хватать, быть достаточным",
  "sufficient": "достаточный",
  "suffocate": "задыхаться",
  "suggest": "предлагать",
  "suit": ["костюм, комплект", "подходить, соответствовать"],
  "suitcase": "чемодан",
  "suite": "апартаменты, номер люкс",
  "sulfur (sulphur)": "сера",
  "sum": "сумма, суммировать",
  "sum up": "подытожить",
  "summary": "сводка, конспект",
  "summit": "вершина, верх",
  "summon": "вызывать",
  "sunset": "закат солнца",
  "superb": "превосходный",
  "superficial": "поверхностный",
  "superintendent": "управляющий, начальник",
  "superior": "высший, превосходящий",
  "supervise": "надзирать, контролировать",
  "supplement": "дополнение, дополнять",
  "supply": ["поставлять, поставка", "предложение"],
  "support": "поддерживать",
  "suppose": "полагать",
  "suppress": "подавлять, удерживать",
  "supreme": "высший,  верховный",
  "sure": "уверенный",
  "surf": "прибой",
  "surface": "поверхность",
  "surge": "волна, всплеск, вздыматься",
  "surgery": "хирургия, операция",
  "surpass": "превзойти",
  "surplus": "избыток, излишек (экон.)",
  "surprise": "удивлять, удивление",
  "surrender": "сдаваться, капитулировать",
  "surround": "окружать",
  "surveillance": "наблюдение",
  "survey": "обзор, исследование",
  "survive": "выжить",
  "susceptible": "восприимчивый, подверженный",
  "suspect": "подозревать, подозреваемый",
  "suspend": "приостановить, подвесить",
  "suspicious": "подозрительный",
  "sustain": "поддерживать",
  "swallow": "проглатывать, глоток",
  "swamp": "болото, топь",
  "swan": "лебедь",
  "swap": "менять, обмен",
  "swarm": "рой, роиться, толпиться",
  "sway": "раскачивать",
  "swear": ["клясться", "ругаться"],
  "sweat": "пот, потеть",
  "sweep": "размах, охват",
  "sweep (swept, swept)": "подметать",
  "sweetheart": "возлюбленный (ая), милый",
  "swell (swelled, swollen)": "раздуваться, распухать",
  "swift": "быстрый, скорый",
  "swing (swung, swung)": "качать, махать",
  "swirl": "кружить, вихрь, водоворот",
  "switch": "переключать, переключатель",
  "swoop": "кинуться, напасть",
  "sword": "меч",
  "syllable": "слог",
  "symbol": "символ",
  "sympathy": "сочуствие",
  "syringe": "шприц"
}
